nonebot_plugin_wutheringwaves/__init__.py
nonebot_plugin_wutheringwaves/_version.py
nonebot_plugin_wutheringwaves/api/__init__.py
nonebot_plugin_wutheringwaves/api/game_sign.py
nonebot_plugin_wutheringwaves/api/login.py
nonebot_plugin_wutheringwaves/api/task_process.py
nonebot_plugin_wutheringwaves/command/__init__.py
nonebot_plugin_wutheringwaves/command/common.py
nonebot_plugin_wutheringwaves/command/login.py
nonebot_plugin_wutheringwaves/command/sign.py
nonebot_plugin_wutheringwaves/command/strategy.py
nonebot_plugin_wutheringwaves/command/task.py
nonebot_plugin_wutheringwaves/model/__init__.py
nonebot_plugin_wutheringwaves/model/common.py
nonebot_plugin_wutheringwaves/model/config.py
nonebot_plugin_wutheringwaves/model/requests.py
nonebot_plugin_wutheringwaves/resources/role_alias.json
nonebot_plugin_wutheringwaves/resources/一图流/丹瑾.jpg
nonebot_plugin_wutheringwaves/resources/一图流/凌阳.jpg
nonebot_plugin_wutheringwaves/resources/一图流/卡卡罗.jpg
nonebot_plugin_wutheringwaves/resources/一图流/吟霖.jpg
nonebot_plugin_wutheringwaves/resources/一图流/安可.jpg
nonebot_plugin_wutheringwaves/resources/一图流/忌炎.jpg
nonebot_plugin_wutheringwaves/resources/一图流/散华.jpg
nonebot_plugin_wutheringwaves/resources/一图流/漂泊者-湮灭.jpg
nonebot_plugin_wutheringwaves/resources/一图流/炽霞.jpg
nonebot_plugin_wutheringwaves/resources/一图流/维里奈.jpg
nonebot_plugin_wutheringwaves/resources/一图流/鉴心.jpg
nonebot_plugin_wutheringwaves/utils/__init__.py
nonebot_plugin_wutheringwaves/utils/common.py
nonebot_plugin_wutheringwaves/utils/logger.py
nonebot_plugin_wutheringwaves-0.1.1.dist-info/METADATA
nonebot_plugin_wutheringwaves-0.1.1.dist-info/WHEEL
nonebot_plugin_wutheringwaves-0.1.1.dist-info/RECORD
