Metadata-Version: 2.1
Name: nonebot-plugin-wutheringwaves
Version: 0.1.1
Summary: 
Author: Night-stars-1
Author-email: nujj1042633805@gmail.com
Requires-Python: >=3.11,<4.0
Classifier: Programming Language :: Python :: 3
Classifier: Programming Language :: Python :: 3.11
Classifier: Programming Language :: Python :: 3.12
Requires-Dist: httpx (>=0.27.0,<0.28.0)
Requires-Dist: nonebot-adapter-console (>=0.5.0,<0.6.0)
Requires-Dist: nonebot-adapter-onebot (>=2.4.3,<3.0.0)
Requires-Dist: nonebot-plugin-apscheduler (>=0.4.0,<0.5.0)
Requires-Dist: nonebot-plugin-send-anything-anywhere (>=0.6.1,<0.7.0)
Requires-Dist: nonebot2[fastapi] (>=2.3.1,<3.0.0)
Project-URL: homepage, https://github.com/Night-stars-1
Project-URL: repository, https://github.com/Night-stars-1/nonebot-plugin-wutheringwaves
